mpepool.py
mpewui.py
pyexpool-3.2.1.data/data/share/pyexpool/views/restapi.md
pyexpool-3.2.1.data/data/share/pyexpool/views/webui.tpl
pyexpool-3.2.1.dist-info/LICENSE.txt
pyexpool-3.2.1.dist-info/METADATA
pyexpool-3.2.1.dist-info/RECORD
pyexpool-3.2.1.dist-info/WHEEL
pyexpool-3.2.1.dist-info/top_level.txt
