Metadata-Version: 2.1
Name: pyexpool
Version: 3.2.1
Summary: A lightweight multi-process Execution Pool with load balancing and customizable resource consumption constraints.
Home-page: https://github.com/eXascaleInfolab/PyExPool
Author: Artem Lutov
Author-email: artem@exascale.info
License: UNKNOWN
Project-URL: Source, https://github.com/eXascaleInfolab/PyExPool
Project-URL: Visit our eXascale Infolab, https://exascale.info/
Project-URL: Bug Reports & Proposals, https://github.com/eXascaleInfolab/PyExPool/issues
Keywords: execution-pool load-balancer task-queue multi-process benchmarking-framework execution-constraints NUMA concurrent parallel-computing cache-control monitoring-server
Platform: UNKNOWN
Classifier: Development Status :: 4 - Beta
Classifier: Environment :: Plugins
Classifier: Environment :: Console
Classifier: Intended Audience :: Developers
Classifier: Intended Audience :: Information Technology
Classifier: Intended Audience :: Science/Research
Classifier: Intended Audience :: System Administrators
Classifier: License :: OSI Approved :: Apache Software License
Classifier: Natural Language :: English
Classifier: Operating System :: POSIX
Classifier: Operating System :: Android
Classifier: Operating System :: Unix
Classifier: Operating System :: MacOS
Classifier: Operating System :: Microsoft
Classifier: Operating System :: OS Independent
Classifier: Programming Language :: Python :: 2
Classifier: Programming Language :: Python :: 2.7
Classifier: Programming Language :: Python :: 3
Classifier: Programming Language :: Python :: 3.4
Classifier: Programming Language :: Python :: 3.5
Classifier: Programming Language :: Python :: 3.6
Classifier: Programming Language :: Python :: 3.7
Classifier: Programming Language :: Python :: Implementation :: CPython
Classifier: Programming Language :: Python :: Implementation :: PyPy
Classifier: Topic :: System :: Benchmark
Classifier: Topic :: System :: Monitoring
Classifier: Topic :: Software Development :: Libraries :: Application Frameworks
Classifier: Topic :: Software Development :: Testing
Classifier: Topic :: Software Development :: Libraries :: Python Modules
Classifier: Topic :: Software Development
Classifier: Topic :: Scientific/Engineering
Provides-Extra: test
Requires-Dist: psutil (>=5)
Requires-Dist: bottle
Requires-Dist: future; python_version < "3"
Requires-Dist: enum34 (>=1); python_version < "3.4"
Provides-Extra: test
Provides-Extra: test
Requires-Dist: mock (>=2); (python_version < "3") and extra == 'test'
